src/__init__.py
src/main.py
src/lib/Commands.py
src/lib/__init__.py
Local_Xampp_Apache-0.0.3.dist-info/METADATA
Local_Xampp_Apache-0.0.3.dist-info/WHEEL
Local_Xampp_Apache-0.0.3.dist-info/entry_points.txt
Local_Xampp_Apache-0.0.3.dist-info/top_level.txt
Local_Xampp_Apache-0.0.3.dist-info/RECORD
