Metadata-Version: 2.1
Name: Local-Xampp-Apache
Version: 0.0.3
Summary: Access the Windows XamPP Apache Server via Command lines
Home-page: https://git.selfmade.ninja/SRIDHARDSCV/automate_xampp_windows
Author: Sridhar
Author-email: sridhardscv@gmail.com
Requires-Python: >=3.6
Requires-Dist: subprocess.run (>=0.0.8)
Requires-Dist: psutil (>5.9.4)
Requires-Dist: argparse (>=1.4.0)
